topsis/__init__.py
topsis/topsis.py
topsis_testing_2025-0.3.0.dist-info/LICENSE
topsis_testing_2025-0.3.0.dist-info/METADATA
topsis_testing_2025-0.3.0.dist-info/WHEEL
topsis_testing_2025-0.3.0.dist-info/entry_points.txt
topsis_testing_2025-0.3.0.dist-info/top_level.txt
topsis_testing_2025-0.3.0.dist-info/RECORD
