Metadata-Version: 2.2
Name: topsis_testing_2025
Version: 0.3.0
Summary: TOPSIS Python Package
Home-page: https://github.com/yourusername/topsis
Author: Your Name
Author-email: your_email@example.com
Requires-Python: >=3.6
License-File: LICENSE
Requires-Dist: pandas
Requires-Dist: numpy
Dynamic: author
Dynamic: author-email
Dynamic: description
Dynamic: description-content-type
Dynamic: home-page
Dynamic: requires-dist
Dynamic: requires-python
Dynamic: summary
